dspy_qdrant/__init__.py
dspy_qdrant/py.typed
dspy_qdrant/qdrant_rm.py
dspy_qdrant-0.1.4.dist-info/METADATA
dspy_qdrant-0.1.4.dist-info/WHEEL
dspy_qdrant-0.1.4.dist-info/licenses/LICENSE
dspy_qdrant-0.1.4.dist-info/RECORD
