Metadata-Version: 2.4
Name: dspy-qdrant
Version: 0.1.4
Summary: Qdrant powered retriever for DSPy
Author-email: Anush008 <anush.shett@qdrant.com>
License:                                  Apache License
License-File: LICENSE
Requires-Python: >=3.11
Requires-Dist: dspy
Requires-Dist: qdrant-client>=1.14.2
